lambdarest/__init__.py
lambdarest-13.0.3.dist-info/LICENSE
lambdarest-13.0.3.dist-info/METADATA
lambdarest-13.0.3.dist-info/WHEEL
lambdarest-13.0.3.dist-info/top_level.txt
lambdarest-13.0.3.dist-info/RECORD
