Metadata-Version: 2.1
Name: lambdarest
Version: 13.0.3
Summary: flask like web framework for AWS Lambda
Author-email: Johannes Valbjørn <johannes.valbjorn@gmail.com>
License: MIT License
Project-URL: Homepage, https://github.com/sloev/python-lambdarest
Keywords: lambda,aws,awslambda,flask,web,jsonschema,werkzeug
Classifier: Development Status :: 6 - Mature
Classifier: Intended Audience :: Developers
Classifier: Natural Language :: English
Classifier: Programming Language :: Python :: 3.7
Classifier: Programming Language :: Python :: 3.8
Classifier: Programming Language :: Python :: 3.9
Classifier: Programming Language :: Python :: 3.10
Classifier: Programming Language :: Python :: 3.11
Requires-Python: >=3.7
License-File: LICENSE
Requires-Dist: jsonschema (>=4.4.0)
Requires-Dist: strict-rfc3339 (>=0.7)
Requires-Dist: werkzeug (>=2.2.3)
Provides-Extra: dev
Requires-Dist: pytest (>=7.1.0) ; extra == 'dev'
Requires-Dist: PyYaml (>=5.3.1) ; extra == 'dev'
Requires-Dist: mock (>=4.0.2) ; extra == 'dev'
Requires-Dist: pytest-readme (>=1.0.1) ; extra == 'dev'
Requires-Dist: black (>=22.3.0) ; extra == 'dev'
